LICENSE
guap/__init__.py
guap/metrics/__init__.py
guap/metrics/classification.py
guap-0.1.4.dist-info/LICENSE
guap-0.1.4.dist-info/WHEEL
guap-0.1.4.dist-info/METADATA
guap-0.1.4.dist-info/RECORD
