Metadata-Version: 2.1
Name: guap
Version: 0.1.4
Summary: 
Home-page: https://github.com/guap-ml/guap
License: Apache-2.0
Keywords: Python,Machine Learning,Evaluation Metrics
Author: Ulysse Bottello
Author-email: ulysse@guap.ml
Requires-Python: >=3.7,<4.0
Classifier: Development Status :: 1 - Planning
Classifier: Environment :: Console
Classifier: Intended Audience :: Information Technology
Classifier: License :: OSI Approved :: Apache Software License
Classifier: Operating System :: OS Independent
Classifier: Programming Language :: Python :: 3
Classifier: Programming Language :: Python :: 3.7
Classifier: Programming Language :: Python :: 3.8
Classifier: Programming Language :: Python :: 3.9
Classifier: Topic :: Scientific/Engineering :: Artificial Intelligence
Classifier: Topic :: Software Development
Requires-Dist: loguru (>=0.5.3,<0.6.0)
Requires-Dist: numpy (>=1.20.2,<2.0.0)
Requires-Dist: sklearn (>=0.0,<0.1)
Project-URL: Repository, https://github.com/guap-ml/guap
